LICENSE
MANIFEST.in
README.rst
marchanddesable.py
setup.py
test.py
marchanddesable.egg-info/PKG-INFO
marchanddesable.egg-info/SOURCES.txt
marchanddesable.egg-info/dependency_links.txt
marchanddesable.egg-info/entry_points.txt
marchanddesable.egg-info/top_level.txt