Metadata-Version: 1.1
Name: marchanddesable
Version: 0.2
Summary: Turn off your server when you sleep
Home-page: https://github.com/madjar/marchanddesable
Author: Georges Dubus
Author-email: georges.dubus@compiletoi.net
License: ISC
Platform: UNKNOWN
Classifier: License :: OSI Approved :: ISC License (ISCL)
Classifier: Development Status :: 2 - Pre-Alpha
Classifier: Programming Language :: Python
Classifier: Programming Language :: Python :: 3
